hgext3rd/convert_prcs/__init__.py
hgext3rd/convert_prcs/prcs.py
hg_convert_prcs_extension-2.0.0.dist-info/COPYING
hg_convert_prcs_extension-2.0.0.dist-info/METADATA
hg_convert_prcs_extension-2.0.0.dist-info/WHEEL
hg_convert_prcs_extension-2.0.0.dist-info/top_level.txt
hg_convert_prcs_extension-2.0.0.dist-info/zip-safe
hg_convert_prcs_extension-2.0.0.dist-info/RECORD
