Metadata-Version: 2.1
Name: hg-convert-prcs-extension
Version: 2.0.0
Summary: PRCS source for the Mercurial convert extension.
Home-page: https://vx68k.bitbucket.io/hg-convert-prcs/
Author: Kaz Nishimura
Author-email: kazssym@linuxfront.com
License: UNKNOWN
Project-URL: Source, https://github.com/vx68k/hg-convert-prcs-extension
Platform: UNKNOWN
Classifier: License :: OSI Approved :: GNU General Public License v3 or later (GPLv3+)
Classifier: Programming Language :: Python :: 3
Classifier: Programming Language :: Python :: 2.7
Classifier: Topic :: Software Development :: Version Control
Requires-Python: >=2.7
Requires-Dist: mercurial (>=4.7)
Requires-Dist: prcslib (>=4.1)
